inviter2/__init__.py
inviter2/forms.py
inviter2/models.py
inviter2/tests.py
inviter2/tokens.py
inviter2/urls.py
inviter2/utils.py
inviter2/views.py
inviter2/migrations/0001_initial.py
inviter2/migrations/__init__.py
inviter2/templates/inviter2/done.html
inviter2/templates/inviter2/opt-out-done.html
inviter2/templates/inviter2/opt-out.html
inviter2/templates/inviter2/register.html
inviter2/templates/inviter2/email/body.txt
inviter2/templates/inviter2/email/subject.txt
django_inviter2-1.4.0.dist-info/AUTHORS
django_inviter2-1.4.0.dist-info/LICENSE
django_inviter2-1.4.0.dist-info/METADATA
django_inviter2-1.4.0.dist-info/WHEEL
django_inviter2-1.4.0.dist-info/top_level.txt
django_inviter2-1.4.0.dist-info/RECORD
