Metadata-Version: 2.1
Name: django-inviter2
Version: 1.4.0
Summary: Simple email invitations for your Django app
Home-page: https://github.com/mjschultz/django-inviter2
Author: Michael J Schultz
Author-email: mjschultz@gmail.com
License: UNKNOWN
Platform: UNKNOWN
Classifier: Environment :: Web Environment
Classifier: Intended Audience :: Developers
Classifier: License :: OSI Approved :: BSD License
Classifier: Operating System :: OS Independent
Classifier: Framework :: Django
Classifier: Programming Language :: Python
Classifier: Programming Language :: Python :: 2
Classifier: Programming Language :: Python :: 2.7
Classifier: Programming Language :: Python :: 3
Classifier: Programming Language :: Python :: 3.3
Classifier: Programming Language :: Python :: 3.4
Classifier: Programming Language :: Python :: 3.5
Requires-Dist: shortuuid (>=0.1)
Requires-Dist: six
Requires-Dist: Django (>=1.4)
